gateforge/__init__.py
gateforge/__main__.py
gateforge/compiler.py
gateforge/concepts.py
gateforge/core.py
gateforge/dsl.py
gateforge/py.typed
gateforge/verilator.py
gateforge/verilator_cpp.py
gateforge-0.0.4.dist-info/METADATA
gateforge-0.0.4.dist-info/WHEEL
gateforge-0.0.4.dist-info/licenses/LICENSE
gateforge-0.0.4.dist-info/RECORD
