Metadata-Version: 2.4
Name: gateforge
Version: 0.0.4
Summary: Framework for designing Register-Transfer Level (RTL) hardware
Project-URL: Homepage, https://github.com/vagran/GateForge
Project-URL: Issues, https://github.com/vagran/GateForge/issues
Author-email: Artyom Lebedev <artyom.lebedev@gmail.com>
License-Expression: Apache-2.0
License-File: LICENSE
Classifier: Operating System :: OS Independent
Classifier: Programming Language :: Python :: 3
Requires-Python: >=3.8
